apsniper0673_configreader-0.1.8.dist-info/licenses/LICENSE
myconfigreader/__init__.py
myconfigreader/config_reader.py
apsniper0673_configreader-0.1.8.dist-info/METADATA
apsniper0673_configreader-0.1.8.dist-info/WHEEL
apsniper0673_configreader-0.1.8.dist-info/top_level.txt
apsniper0673_configreader-0.1.8.dist-info/RECORD
