Metadata-Version: 2.4
Name: apsniper0673_configreader
Version: 0.1.8
Summary: My config reader package
Author: sniper0673
Requires-Python: >=3.8
License-File: LICENSE
Dynamic: license-file
